{
  "version": "0.1.0",
  "name": "newsreport",
  "instructions": [
    {
      "name": "initialize",
      "accounts": [
        {
          "name": "reportAccount",
          "isMut": true,
          "isSigner": true
        },
        {
          "name": "authority",
          "isMut": true,
          "isSigner": true
        },
        {
          "name": "systemProgram",
          "isMut": false,
          "isSigner": false
        }
      ],
      "args": []
    },
    {
      "name": "updateReport",
      "accounts": [
        {
          "name": "reportAccount",
          "isMut": true,
          "isSigner": false
        },
        {
          "name": "authority",
          "isMut": false,
          "isSigner": true
        },
        {
          "name": "systemProgram",
          "isMut": false,
          "isSigner": false
        }
      ],
      "args": [
        {
          "name": "reportUri",
          "type": "string"
        }
      ]
    },
    {
      "name": "pushForVote",
      "accounts": [
        {
          "name": "reportAccount",
          "isMut": true,
          "isSigner": false
        },
        {
          "name": "authority",
          "isMut": false,
          "isSigner": true
        },
        {
          "name": "systemProgram",
          "isMut": false,
          "isSigner": false
        }
      ],
      "args": [
        {
          "name": "reportUri",
          "type": "string"
        },
        {
          "name": "payamt",
          "type": "u32"
        }
      ]
    }
  ],
  "accounts": [
    {
      "name": "ReportAccount",
      "type": {
        "kind": "struct",
        "fields": [
          {
            "name": "uri",
            "type": "string"
          },
          {
            "name": "authority",
            "type": "publicKey"
          },
          {
            "name": "status",
            "type": "u8"
          },
          {
            "name": "readpayment",
            "type": "u32"
          }
        ]
      }
    }
  ],
  "metadata": {
    "address": "3Z8eqLzepWH6UmqFyU9mDsjQp6QepLURqHSBFwmJLdCh"
  }
}
